colorpro
colorpro.py
setup.py
colorpro.egg-info/PKG-INFO
colorpro.egg-info/SOURCES.txt
colorpro.egg-info/dependency_links.txt
colorpro.egg-info/requires.txt
colorpro.egg-info/top_level.txt