Metadata-Version: 1.1
Name: colorpro
Version: 0.2
Summary: Python based optionated color transformation tool.
Home-page: http://github.com/sebastian-software/colorpro
Author: Sebastian Software
Author-email: team@sebastian-software.de
License: MIT
Download-URL: http://pypi.python.org/packages/source/c/colorpro/colorpro-0.2.zip
Platform: any
Classifier: Development Status :: 3 - Alpha
Classifier: Environment :: Console
Classifier: Intended Audience :: Developers
Classifier: License :: OSI Approved :: MIT License
Classifier: License :: Freely Distributable
Classifier: Operating System :: OS Independent
Classifier: Programming Language :: Python
Classifier: Programming Language :: Python :: 3.3
Classifier: Programming Language :: Python :: 3.4
Classifier: Programming Language :: Python :: 3.5
Classifier: Topic :: Software Development
